metainfoyaml2py/__init__.py
metainfoyaml2py/metainfoyaml2py.py
metainfoyaml2py/resources/standard_file_content.yaml
metainfoyaml2py/resources/standard_plugin_content/LICENSE
metainfoyaml2py/resources/standard_plugin_content/README.md
metainfoyaml2py/resources/standard_plugin_content/nomad.yaml
metainfoyaml2py/resources/standard_plugin_content/pyproject.toml
metainfoyaml2py/resources/standard_plugin_content/setup.py
metainfoyaml2py/resources/standard_plugin_content/src/plugin_name/__init__.py
metainfoyaml2py/resources/standard_plugin_content/src/plugin_name/nomad_plugin.yaml
metainfoyaml2py/resources/standard_plugin_content/tests/test_schema.py
metainfoyaml2py/resources/standard_plugin_content/tests/data/README.md
metainfoyaml2py-0.0.13.dist-info/licenses/LICENSE
metainfoyaml2py-0.0.13.dist-info/METADATA
metainfoyaml2py-0.0.13.dist-info/WHEEL
metainfoyaml2py-0.0.13.dist-info/entry_points.txt
metainfoyaml2py-0.0.13.dist-info/top_level.txt
metainfoyaml2py-0.0.13.dist-info/RECORD
