Metadata-Version: 2.4
Name: metainfoyaml2py
Version: 0.0.13
Summary: A program for converting NOMAD metainfo YAML schemas into Python class definitions
Author-email: Hampus Näsström <hampus.naesstroem@physik.hu-berlin.de>
Maintainer-email: Hampus Näsström <hampus.naesstroem@physik.hu-berlin.de>
License: Apache-2.0
Project-URL: Homepage, https://github.com/hampusnasstrom/metainfo-yaml2py
Project-URL: Bug Tracker, https://github.com/hampusnasstrom/metainfo-yaml2py/issues
Keywords: nomad
Classifier: Programming Language :: Python :: 3
Classifier: Programming Language :: Python :: 3 :: Only
Classifier: Programming Language :: Python :: 3.9
Classifier: License :: OSI Approved :: Apache Software License
Requires-Python: >=3.9
License-File: LICENSE
Requires-Dist: autopep8>=1.7.0
Requires-Dist: autoflake>=1.6.1
Requires-Dist: PyYAML>=6.0
Requires-Dist: toml>=0.10.2
Provides-Extra: dev
Requires-Dist: nomad-lab>=1.2.0-pre; extra == "dev"
Requires-Dist: structlog; extra == "dev"
Dynamic: license-file
